LICENSE
MANIFEST.in
README.md
setup.cfg
setup.py
docassemble/__init__.py
docassemble.wsunhelloworld.egg-info/PKG-INFO
docassemble.wsunhelloworld.egg-info/SOURCES.txt
docassemble.wsunhelloworld.egg-info/dependency_links.txt
docassemble.wsunhelloworld.egg-info/namespace_packages.txt
docassemble.wsunhelloworld.egg-info/not-zip-safe
docassemble.wsunhelloworld.egg-info/top_level.txt
docassemble/wsunhelloworld/__init__.py
docassemble/wsunhelloworld/data/questions/hello.yml
docassemble/wsunhelloworld/data/sources/README.md
docassemble/wsunhelloworld/data/static/README.md
docassemble/wsunhelloworld/data/templates/README.md
docassemble/wsunhelloworld/data/templates/hello_planet.docx