Metadata-Version: 2.1
Name: docassemble.wsunhelloworld
Version: 0.0.1
Summary: A docassemble extension.
Home-page: https://docassemble.org
Author: William Sun
Author-email: wsun@corelogic.com
License: The MIT License (MIT)
Platform: UNKNOWN
